app/__init__.py
app/menu.py
app/Address_book/AdressBook.py
app/Address_book/Class.py
app/Address_book/__init__.py
app/Notebook/__init__.py
app/Notebook/decorator.py
app/Notebook/notes.py
app/Notebook/notesclass.py
app/Sorter/__init__.py
app/Sorter/sort.py
Apllepy_personal_assistant-0.1.6.dist-info/LICENSE
Apllepy_personal_assistant-0.1.6.dist-info/METADATA
Apllepy_personal_assistant-0.1.6.dist-info/WHEEL
Apllepy_personal_assistant-0.1.6.dist-info/entry_points.txt
Apllepy_personal_assistant-0.1.6.dist-info/top_level.txt
Apllepy_personal_assistant-0.1.6.dist-info/RECORD
