Metadata-Version: 2.1
Name: Apllepy-personal-assistant
Version: 0.1.6
Summary: Apllepy-personal-assistant
Home-page: https://github.com/IgorPupynin/Project_group6
Author: Pupinin Igor, Valentyna Gordynska, Shevtsova Tetyana, Svitelskyi Andriy
License: MIT
License-File: LICENSE
